XStatic_Angular_Gettext-2.4.1.0-py3.6-nspkg.pth
xstatic/pkg/angular_gettext/__init__.py
xstatic/pkg/angular_gettext/data/angular-gettext.js
XStatic_Angular_Gettext-2.4.1.0.dist-info/LICENSE
XStatic_Angular_Gettext-2.4.1.0.dist-info/METADATA
XStatic_Angular_Gettext-2.4.1.0.dist-info/WHEEL
XStatic_Angular_Gettext-2.4.1.0.dist-info/namespace_packages.txt
XStatic_Angular_Gettext-2.4.1.0.dist-info/top_level.txt
XStatic_Angular_Gettext-2.4.1.0.dist-info/RECORD
