Metadata-Version: 2.1
Name: XStatic-Angular-Gettext
Version: 2.4.1.0
Summary: Angular-Gettext 2.4.1 (XStatic packaging standard)
Home-page: https://angular-gettext.rocketeer.be/
Maintainer: Radomir Dopieralski
Maintainer-email: openstack@sheep.art.pl
License: MIT
Keywords: angular_gettext xstatic
Platform: any
